[{"displayUrl": "https://en.wikipedia.org/wiki/Biathlon_World_Championships_2015...", "name": "Biathlon World Championships 2015 \u2013 Men's pursuit - Wikipedia", "id": "https://api.cognitive.microsoft.com/api/v5/#WebPages.0", "dateLastCrawled": "2016-11-05T04:33:00", "snippet": "Penalties (P+P+S+S) Time Deficit; 5: Erik Lesser ... Bulgaria: 0:40: 2 (0+0+1+1) 31:33.8 +45.9: 7: 12: Martin Fourcade", "url": "https://www.bing.com/cr?IG=663833CF4AF54F5F8B4F138E6BD69C76&CID=0D95D220473A6F6F09CEDBF746DD6E74&rd=1&h=ou9cc8OMGT7fUsMmzsOb6aJWTX3_a368Bxd_fMfb3bk&v=1&r=https%3a%2f%2fen.wikipedia.org%2fwiki%2fBiathlon_World_Championships_2015_%25E2%2580%2593_Men%2527s_pursuit&p=DevEx,5063.1"}, {"displayUrl": "https://en.wikipedia.org/wiki/Biathlon_World_Championships_2016...", "name": "Biathlon World Championships 2016 \u2013 Women's pursuit ...", "id": "https://api.cognitive.microsoft.com/api/v5/#WebPages.1", "dateLastCrawled": "2016-10-08T22:01:00", "snippet": "Penalties (P+P+S+S) Time Deficit; 3: Laura Dahlmeier ... Bulgaria: 2:09: 1 (0+0+0+1) 35:06.0 +4:16.8: 39: 6: Mona Brorsson", "url": "https://www.bing.com/cr?IG=663833CF4AF54F5F8B4F138E6BD69C76&CID=0D95D220473A6F6F09CEDBF746DD6E74&rd=1&h=wggXQfMOUVuL90Mdp5syoVpG0FcApsi-70tcChw0Q2M&v=1&r=https%3a%2f%2fen.wikipedia.org%2fwiki%2fBiathlon_World_Championships_2016_%25E2%2580%2593_Women%2527s_pursuit&p=DevEx,5077.1"}, {"displayUrl": "www.digplanet.com/wiki/Biathlon_World_Championships_2016_\u2013_Men's...", "name": "Learn and talk about Biathlon World Championships 2016 ...", "id": "https://api.cognitive.microsoft.com/api/v5/#WebPages.2", "dateLastCrawled": "2016-10-13T05:13:00", "snippet": "Penalties (P+P+S+S) Time Deficit ...", "url": "http://www.bing.com/cr?IG=663833CF4AF54F5F8B4F138E6BD69C76&CID=0D95D220473A6F6F09CEDBF746DD6E74&rd=1&h=cDFOrB4h-L6futEa_HSh7Yg_pD1Upgnnu-qjwkCtUu0&v=1&r=http%3a%2f%2fwww.digplanet.com%2fwiki%2fBiathlon_World_Championships_2016_%25E2%2580%2593_Men%2527s_pursuit&p=DevEx,5088.1"}, {"displayUrl": "www.digplanet.com/wiki/Biathlon_World_Championships_2013_\u2013_Men's...", "name": "Learn and talk about Biathlon World Championships 2013 ...", "id": "https://api.cognitive.microsoft.com/api/v5/#WebPages.3", "dateLastCrawled": "2016-11-15T13:12:00", "snippet": "Penalties (P+P+S+S) Time Deficit; 1: Emil Hegle Svendsen ... Bulgaria: 2:03: 5 (1+1+2+1) 36:43.4 +4:07.9: 40: 40: Edgars Piksons", "url": "http://www.bing.com/cr?IG=663833CF4AF54F5F8B4F138E6BD69C76&CID=0D95D220473A6F6F09CEDBF746DD6E74&rd=1&h=Q2ejYP8_V2wxP_52R8VFJYhP3M_QHmC2UkrzSHctkGY&v=1&r=http%3a%2f%2fwww.digplanet.com%2fwiki%2fBiathlon_World_Championships_2013_%25E2%2580%2593_Men%2527s_pursuit&p=DevEx,5099.1"}, {"displayUrl": "www.thefullwiki.org/Biathlon_at_the_2010_Winter_Olympics_\u2013_Men's...", "name": "Biathlon at the 2010 Winter Olympics \u2013 Men's pursuit - The ...", "id": "https://api.cognitive.microsoft.com/api/v5/#WebPages.4", "dateLastCrawled": "2016-11-01T01:09:00", "snippet": "The men's pursuit competition in biathlon at the Vancouver 2010 Olympics was held at Whistler Olympic Park in Whistler, British Columbia on February 16, 2010.", "url": "http://www.bing.com/cr?IG=663833CF4AF54F5F8B4F138E6BD69C76&CID=0D95D220473A6F6F09CEDBF746DD6E74&rd=1&h=yvLS-8VUZruBX-zDFxUHfe3-i0GVXFE69-ihEskYimk&v=1&r=http%3a%2f%2fwww.thefullwiki.org%2fBiathlon_at_the_2010_Winter_Olympics_%25E2%2580%2593_Men%2527s_pursuit&p=DevEx,5111.1"}, {"displayUrl": "www.revolvy.com/main/index.php?s=2016 Women", "name": "2016 Women - revolvy.com", "id": "https://api.cognitive.microsoft.com/api/v5/#WebPages.5", "dateLastCrawled": "2016-10-31T00:43:00", "snippet": "Express yourself. Organize your knowledge. Expand your mind. Discover the world. Revolvy connects you with interesting topics, lists and quizzes. Choose from hundreds ...", "url": "http://www.bing.com/cr?IG=663833CF4AF54F5F8B4F138E6BD69C76&CID=0D95D220473A6F6F09CEDBF746DD6E74&rd=1&h=J70B9wfQN97OgH6c8G-xqTM2vQEg94k94R3fluKvM-w&v=1&r=http%3a%2f%2fwww.revolvy.com%2fmain%2findex.php%3fs%3d2016%2520Women&p=DevEx,5123.1"}, {"about": [{"name": "Biathlon at the 2014 Winter Olympics \u2013 Men's pursuit"}], "displayUrl": "https://en.m.wikipedia.org/wiki/Biathlon_at_the_2014_Winter...", "name": "Biathlon at the 2014 Winter Olympics \u2013 Men's pursuit ...", "id": "https://api.cognitive.microsoft.com/api/v5/#WebPages.6", "dateLastCrawled": "2016-10-29T23:58:00", "snippet": "Penalties (P+P+S+S) Deficit ...", "url": "https://www.bing.com/cr?IG=663833CF4AF54F5F8B4F138E6BD69C76&CID=0D95D220473A6F6F09CEDBF746DD6E74&rd=1&h=C6IqxyOrBQcakc8R-gzJWOiyOac43L-jHTA5xctpT_U&v=1&r=https%3a%2f%2fen.m.wikipedia.org%2fwiki%2fBiathlon_at_the_2014_Winter_Olympics_%25E2%2580%2593_Men%2527s_pursuit&p=DevEx,5134.1"}, {"displayUrl": "https://no.wikipedia.org/wiki/Skiskyting_under_Vinter-OL_2014...", "name": "Skiskyting under Vinter-OL 2014 \u2013 Jaktstart menn \u2013 Wikipedia", "id": "https://api.cognitive.microsoft.com/api/v5/#WebPages.7", "dateLastCrawled": "2016-10-28T20:03:00", "snippet": "Penalties (P+P+S+S) Deficit; 6: Martin Fourcade ... Bulgaria: 2:22: 39:44.6: 7 (3+1+2+1) +5.56.0: 56: 57: Jurij Ljadov", "url": "https://www.bing.com/cr?IG=663833CF4AF54F5F8B4F138E6BD69C76&CID=0D95D220473A6F6F09CEDBF746DD6E74&rd=1&h=UGaNWzEcqEPbyiC34ki1ja70tsNQ13g2QZzX_tC_BlU&v=1&r=https%3a%2f%2fno.wikipedia.org%2fwiki%2fSkiskyting_under_Vinter-OL_2014_%25E2%2580%2593_Jaktstart_menn&p=DevEx,5146.1"}]