[{"displayUrl": "schools-wikipedia.org/wp/e/Economy_of_Africa.htm", "name": "Economy of Africa - Wikipedia for Schools", "id": "https://api.cognitive.microsoft.com/api/v5/#WebPages.0", "dateLastCrawled": "2016-11-04T21:38:00", "snippet": "The economy of Africa consists of the trade, ... Total GDP (nominal) (billion US$) GDP per capita (US$, PPP) ... Gabon: 243900: 2007 est. 40: Af: ...", "url": "http://www.bing.com/cr?IG=C15B856F90D34A759E2DFA9735A547F1&CID=3000D49602466B7A1339DD4103A16A96&rd=1&h=cJP1cqWfu5G58hF02HJSleeI_7pyadWUMz8c3FXCMeQ&v=1&r=http%3a%2f%2fschools-wikipedia.org%2fwp%2fe%2fEconomy_of_Africa.htm&p=DevEx,5055.1"}]