[{"Title": "Baao, Camarines Sur - Wikipedia", "Description": "Melquiades I. Gaite ... \u2022 Total: 106.63 km 2 (41.17 sq mi) Population (2010) \u2022 Total: 54,971 \u2022 Density: 520 ... Banw\u0101an ka Baao; English ...", "ID": "8234cacb-07ec-4531-8d15-5e2e6c7cb06f", "DisplayUrl": "https://en.wikipedia.org/wiki/Baao,_Camarines_Sur", "__metadata": {"uri": "https://api.datamarket.azure.com/Data.ashx/Bing/SearchWeb/v1/Web?Adult='Strict'&WebFileType='HTML'&Query='\"Melquiades I. Gaite\" \"Population (2010)\"'&$skip=0&$top=1", "type": "WebResult"}, "Url": "https://en.wikipedia.org/wiki/Baao,_Camarines_Sur"}]