[{"Title": "List of schools in Saginaw, Michigan - Sensagent.com", "Description": "Definitions of list of schools in saginaw michigan, ... Students (K-12) ... Christ Lutheran School: K: 8: 12: 2: 6: Community Baptist Christian School: PK: 12: 120: 9.8:", "ID": "43f2a7dd-9731-47bc-be61-19cf5f1a073c", "DisplayUrl": "dictionary.sensagent.com/list of schools in saginaw michigan/en-en", "__metadata": {"uri": "https://api.datamarket.azure.com/Data.ashx/Bing/SearchWeb/v1/Web?Adult='Strict'&WebFileType='HTML'&Query='\"Community Baptist Christian School\" \"Students (K-12)\"'&$skip=0&$top=1", "type": "WebResult"}, "Url": "http://dictionary.sensagent.com/list%20of%20schools%20in%20saginaw%20michigan/en-en/"}]