[{"ID": "b435a14d-0808-49c1-ba2a-352871dffeac", "__metadata": {"type": "WebResult", "uri": "https://api.datamarket.azure.com/Data.ashx/Bing/SearchWeb/v1/Web?Query='\"Built over Mayan city of Sihuatehuac\u00e1n.\" \"Year\"'&Adult='Strict'&WebFileType='HTML'&$skip=0&$top=1"}, "Title": "List of cities in the Americas by year of foundation ...", "Description": "List of cities in the Americas by year of foundation ... Built over Mayan city of Sihuatehuac\u00e1n. 1570: Jerez: Zacatecas: Mexico: 1570: Sombrerete: Zacatecas: Mexico:", "DisplayUrl": "https://en.wikipedia.org/wiki/Oldest_cities_in_the_Americas", "Url": "https://en.wikipedia.org/wiki/Oldest_cities_in_the_Americas"}]