[{"Title": "2005 Australian motorcycle Grand Prix - Wikipedia", "Description": "The 2005 Australian motorcycle Grand Prix was the fifteenth round of the 2005 MotoGP Championship. ... Time/Retired Grid Points; 1: ... \u00c1ngel Rodr\u00edguez: Honda +3 ...", "ID": "ff3af25b-3573-4d24-b524-a53bbc7d0a19", "DisplayUrl": "https://en.wikipedia.org/wiki/2005_Australian_motorcycle_Grand_Prix", "__metadata": {"uri": "https://api.datamarket.azure.com/Data.ashx/Bing/SearchWeb/v1/Web?Adult='Strict'&WebFileType='HTML'&Query='\"\u00c1ngel Rodr\u00edguez\" \"Time/Retired\"'&$skip=0&$top=1", "type": "WebResult"}, "Url": "https://en.wikipedia.org/wiki/2005_Australian_motorcycle_Grand_Prix"}, {"Title": "Learn and talk about 2004 Japanese motorcycle Grand Prix ...", "Description": "Learn and talk about 2004 Japanese motorcycle Grand Prix , and check out ... Time/Retired Grid Points; 1: ... \u00c1ngel Rodr\u00edguez: Derbi:", "ID": "a8f5592e-a791-43e3-bce1-387d2b55f282", "DisplayUrl": "www.digplanet.com/wiki/2004_Japanese_motorcycle_Grand_Prix", "__metadata": {"uri": "https://api.datamarket.azure.com/Data.ashx/Bing/SearchWeb/v1/Web?Adult='Strict'&WebFileType='HTML'&Query='\"\u00c1ngel Rodr\u00edguez\" \"Time/Retired\"'&$skip=1&$top=1", "type": "WebResult"}, "Url": "http://www.digplanet.com/wiki/2004_Japanese_motorcycle_Grand_Prix"}, {"Title": "Learn and talk about 2012 Spanish motorcycle Grand Prix ...", "Description": "Learn and talk about 2012 Spanish motorcycle Grand Prix , and check out ... Time/Retired Grid Points; 1: 40: Pol ... \u00c1ngel Rodr\u00edguez: FTR: 17 +37.449: 24: 21: 72:", "ID": "e822fe06-4676-486e-9aa2-3a0f00a79b81", "DisplayUrl": "www.digplanet.com/wiki/2012_Spanish_motorcycle_Grand_Prix", "__metadata": {"uri": "https://api.datamarket.azure.com/Data.ashx/Bing/SearchWeb/v1/Web?Adult='Strict'&WebFileType='HTML'&Query='\"\u00c1ngel Rodr\u00edguez\" \"Time/Retired\"'&$skip=2&$top=1", "type": "WebResult"}, "Url": "http://www.digplanet.com/wiki/2012_Spanish_motorcycle_Grand_Prix"}, {"Title": "2002 Valencian Community motorcycle Grand Prix", "Description": "\u00c1ngel Rodr\u00edguez: Aprilia +1:20.276: 26: 19: Dirk Heidolf: Aprilia +1:24.489: 22: 20: ... Time/Retired Grid Points; 1: Dani Pedrosa: Honda: 42:13.044: 1: 25: 2 ...", "ID": "86a42871-bf82-4196-8b4a-732b0c98ee32", "DisplayUrl": "https://pediaview.com/openpedia/2002_Valencian_Community...", "__metadata": {"uri": "https://api.datamarket.azure.com/Data.ashx/Bing/SearchWeb/v1/Web?Adult='Strict'&WebFileType='HTML'&Query='\"\u00c1ngel Rodr\u00edguez\" \"Time/Retired\"'&$skip=3&$top=1", "type": "WebResult"}, "Url": "https://pediaview.com/openpedia/2002_Valencian_Community_motorcycle_Grand_Prix"}, {"Title": "\u09e8\u09e6\u09e6\u09ec \u09ab\u09cd\u09b0\u09c7\u099e\u09cd\u099a \u09ae\u09cb\u099f\u09b0\u09b8\u09be\u0987\u0995\u09c7\u09b2 \u0997\u09cd\u09b0\u09cd\u09af\u09be\u09a8\u09cd\u09a1 \u09aa\u09cd\u09b0\u09bf\u0995\u09cd\u09b8 - \u0989\u0987\u0995\u09bf\u09aa\u09bf\u09a1\u09bf\u09af\u09bc\u09be", "Description": "\u098f\u0987 \u09a8\u09bf\u09ac\u09a8\u09cd\u09a7\u099f\u09bf english \u09a5\u09c7\u0995\u09c7 \u09ac\u09be\u0982\u09b2\u09be\u09af\u09bc \u0985\u09a8\u09c1\u09ac\u09be\u09a6 \u0995\u09b0\u09be \u09aa\u09cd\u09b0\u09af\u09bc\u09cb\u099c\u09a8\u0964 \u098f\u0987 \u09a8\u09bf\u09ac\u09a8\u09cd\u09a7\u099f\u09bf ...", "ID": "2d6dfcb0-490c-48b1-8fe1-0fd23d11e3fb", "DisplayUrl": "https://bn.wikipedia.org/wiki/\u09e8\u09e6\u09e6\u09ec_\u09ab\u09cd\u09b0\u09c7\u099e\u09cd\u099a...", "__metadata": {"uri": "https://api.datamarket.azure.com/Data.ashx/Bing/SearchWeb/v1/Web?Adult='Strict'&WebFileType='HTML'&Query='\"\u00c1ngel Rodr\u00edguez\" \"Time/Retired\"'&$skip=4&$top=1", "type": "WebResult"}, "Url": "https://bn.wikipedia.org/wiki/%E0%A7%A8%E0%A7%A6%E0%A7%A6%E0%A7%AC_%E0%A6%AB%E0%A7%8D%E0%A6%B0%E0%A7%87%E0%A6%9E%E0%A7%8D%E0%A6%9A_%E0%A6%AE%E0%A7%8B%E0%A6%9F%E0%A6%B0%E0%A6%B8%E0%A6%BE%E0%A6%87%E0%A6%95%E0%A7%87%E0%A6%B2_%E0%A6%97%E0%A7%8D%E0%A6%B0%E0%A7%8D%E0%A6%AF%E0%A6%BE%E0%A6%A8%E0%A7%8D%E0%A6%A1_%E0%A6%AA%E0%A7%8D%E0%A6%B0%E0%A6%BF%E0%A6%95%E0%A7%8D%E0%A6%B8"}, {"Title": "2004 Czech Republic motorcycle Grand Prix - Wikipedia, the ...", "Description": "The 2004 Czech Republic motorcycle Grand Prix was the tenth round of the 2004 MotoGP Championship. ... Time/Retired Grid Points; 1: ... \u00c1ngel Rodr\u00edguez:", "ID": "e7c8b840-0d20-4de5-a33d-99650b4ca467", "DisplayUrl": "https://en.wikipedia.org/wiki/2004_Czech_Republic_motorcycle_Grand...", "__metadata": {"uri": "https://api.datamarket.azure.com/Data.ashx/Bing/SearchWeb/v1/Web?Adult='Strict'&WebFileType='HTML'&Query='\"\u00c1ngel Rodr\u00edguez\" \"Time/Retired\"'&$skip=5&$top=1", "type": "WebResult"}, "Url": "https://en.wikipedia.org/wiki/2004_Czech_Republic_motorcycle_Grand_Prix"}, {"Title": "2004 Japanese motorcycle Grand Prix - WOW.com", "Description": "The 2004 Japanese motorcycle Grand Prix was the twelfth round of the 2004 MotoGP Championship. ... Time/Retired Grid Points; 1: ... \u00c1ngel Rodr\u00edguez: Derbi:", "ID": "e558fd59-339d-476b-8bb1-38b0b6370d08", "DisplayUrl": "www.wow.com/wiki/2004_Japanese_motorcycle_Grand_Prix", "__metadata": {"uri": "https://api.datamarket.azure.com/Data.ashx/Bing/SearchWeb/v1/Web?Adult='Strict'&WebFileType='HTML'&Query='\"\u00c1ngel Rodr\u00edguez\" \"Time/Retired\"'&$skip=6&$top=1", "type": "WebResult"}, "Url": "http://www.wow.com/wiki/2004_Japanese_motorcycle_Grand_Prix"}, {"Title": "2002 Dutch TT - Wikipedia, the free encyclopedia", "Description": "The 2002 Dutch TT was the seventh round of the 2002 MotoGP Championship. ... Time/Retired Grid Points; 1: Marco Melandri: ... \u00c1ngel Rodr\u00edguez: Aprilia +16.130: 7: 6 ...", "ID": "94e1e4e1-88cb-4785-b90a-f98e5741c5e2", "DisplayUrl": "https://en.m.wikipedia.org/wiki/2002_Dutch_TT", "__metadata": {"uri": "https://api.datamarket.azure.com/Data.ashx/Bing/SearchWeb/v1/Web?Adult='Strict'&WebFileType='HTML'&Query='\"\u00c1ngel Rodr\u00edguez\" \"Time/Retired\"'&$skip=7&$top=1", "type": "WebResult"}, "Url": "https://en.m.wikipedia.org/wiki/2002_Dutch_TT"}, {"Title": "MotoGP 4 - Revolvy", "Description": "MotoGP 4 (often stylized as ... \u00c1ngel Rodr\u00edguez; KTM Red ... Classification MotoGP Pos No Rider Manufacturer Laps Time/Retired Grid Points 1 99 Jorge Lorenzo Yamaha ...", "ID": "44810c26-732b-4f48-bedd-3d3d5aa73fda", "DisplayUrl": "www.revolvy.com/main/index.php?s=MotoGP 4", "__metadata": {"uri": "https://api.datamarket.azure.com/Data.ashx/Bing/SearchWeb/v1/Web?Adult='Strict'&WebFileType='HTML'&Query='\"\u00c1ngel Rodr\u00edguez\" \"Time/Retired\"'&$skip=8&$top=1", "type": "WebResult"}, "Url": "http://www.revolvy.com/main/index.php?s=MotoGP%204"}]