[{"Title": "Timberline Lodge ski area - Wikipedia, the free encyclopedia", "ID": "80eb3045-c208-492b-a1c5-def5ebba7545", "DisplayUrl": "https://en.wikipedia.org/wiki/Timberline_Lodge_and_Ski_Area", "Description": "Timberline Lodge ski area is the ski and snowboarding area of ... Top elevation (ft) Bottom elevation ... Jeff Flood Express (Still Creek Basin) detach quad:", "__metadata": {"uri": "https://api.datamarket.azure.com/Data.ashx/Bing/SearchWeb/v1/Web?WebFileType='HTML'&Query='\"Jeff Flood Express (Still Creek Basin)\" \"Top elevation (ft)\"'&Adult='Strict'&$skip=0&$top=1", "type": "WebResult"}, "Url": "https://en.wikipedia.org/wiki/Timberline_Lodge_and_Ski_Area"}, {"Title": "timberline lodge ski area : definition of timberline lodge ...", "ID": "b9dd9060-6c2f-4359-9e2b-e7d7732b0e26", "DisplayUrl": "dictionary.sensagent.com/timberline lodge ski area/en-en", "Description": "Timberline Lodge ski area is the ski and snowboarding area of ... Top elevation (ft) Bottom elevation ... Jeff Flood Express (Still Creek Basin) detach quad:", "__metadata": {"uri": "https://api.datamarket.azure.com/Data.ashx/Bing/SearchWeb/v1/Web?WebFileType='HTML'&Query='\"Jeff Flood Express (Still Creek Basin)\" \"Top elevation (ft)\"'&Adult='Strict'&$skip=1&$top=1", "type": "WebResult"}, "Url": "http://dictionary.sensagent.com/timberline%20lodge%20ski%20area/en-en/"}]